intellifold/__init__.py
intellifold/data/__init__.py
intellifold/data/const.py
intellifold/data/types.py
intellifold/data/augmentation/__init__.py
intellifold/data/augmentation/utils.py
intellifold/data/crop/__init__.py
intellifold/data/crop/boltz.py
intellifold/data/crop/cropper.py
intellifold/data/feature/__init__.py
intellifold/data/feature/featurizer.py
intellifold/data/feature/pad.py
intellifold/data/feature/symmetry.py
intellifold/data/filter/__init__.py
intellifold/data/filter/dynamic/__init__.py
intellifold/data/filter/dynamic/date.py
intellifold/data/filter/dynamic/filter.py
intellifold/data/filter/dynamic/max_residues.py
intellifold/data/filter/dynamic/resolution.py
intellifold/data/filter/dynamic/size.py
intellifold/data/filter/dynamic/subset.py
intellifold/data/filter/static/__init__.py
intellifold/data/filter/static/filter.py
intellifold/data/filter/static/ligand.py
intellifold/data/filter/static/polymer.py
intellifold/data/inference/__init__.py
intellifold/data/inference/data_tools.py
intellifold/data/inference/params.py
intellifold/data/inference/utils.py
intellifold/data/module/__init__.py
intellifold/data/module/inference.py
intellifold/data/module/training.py
intellifold/data/msa/__init__.py
intellifold/data/msa/mmseqs2.py
intellifold/data/parse/__init__.py
intellifold/data/parse/a3m.py
intellifold/data/parse/csv.py
intellifold/data/parse/fasta.py
intellifold/data/parse/schema.py
intellifold/data/parse/yaml.py
intellifold/data/sample/__init__.py
intellifold/data/sample/cluster.py
intellifold/data/sample/distillation.py
intellifold/data/sample/random.py
intellifold/data/sample/sampler.py
intellifold/data/tokenize/__init__.py
intellifold/data/tokenize/boltz.py
intellifold/data/tokenize/tokenizer.py
intellifold/data/write/__init__.py
intellifold/data/write/mmcif.py
intellifold/data/write/pdb.py
intellifold/data/write/utils.py
intellifold/data/write/writer.py
intellifold/openfold/__init__.py
intellifold/openfold/config.py
intellifold-0.1.0.dist-info/LICENSE
intellifold-0.1.0.dist-info/METADATA
intellifold-0.1.0.dist-info/WHEEL
intellifold-0.1.0.dist-info/entry_points.txt
intellifold-0.1.0.dist-info/top_level.txt
intellifold-0.1.0.dist-info/RECORD
