Metadata-Version: 2.2
Name: intellifold
Version: 0.1.0
Summary: IntelliFold: A Controllable Foundation Model for General and Specialized Biomolecular Structure Prediction.
Home-page: https://github.com/IntelliGen-AI/IntelliFold
Author: IntelliGen AI
Author-email: contact@intfold.com
License: Apache 2.0 License
Platform: manylinux1
Requires-Python: >=3.10
License-File: LICENSE
Requires-Dist: accelerate==1.1.1
Requires-Dist: biopython==1.85
Requires-Dist: click==8.1.8
Requires-Dist: deepspeed==0.16.4
Requires-Dist: einops==0.8.0
Requires-Dist: einx==0.3.0
Requires-Dist: ihm==2.5
Requires-Dist: mashumaro==3.14
Requires-Dist: ml_collections==1.0.0
Requires-Dist: modelcif==1.2
Requires-Dist: networkx==3.4.2
Requires-Dist: numba==0.61.0
Requires-Dist: numpy==1.24.0
Requires-Dist: pandas==2.2.3
Requires-Dist: PyYAML==6.0.2
Requires-Dist: rdkit==2024.3.2
Requires-Dist: requests==2.32.3
Requires-Dist: scipy==1.14.1
Requires-Dist: torch==2.6.0
Requires-Dist: torchdiffeq==0.2.5
Requires-Dist: tqdm==4.67.1
Dynamic: author
Dynamic: author-email
Dynamic: home-page
Dynamic: license
Dynamic: platform
Dynamic: requires-dist
Dynamic: requires-python
Dynamic: summary
